[
  {
      "Entidad":"CEN",
      "Afiliados":3989376,
      "Comité_Estatal":32,
      "Distritos Federales":300,
      "Distritos_Locales":"--",
      "Comites_Municipales":"--",
      "Secciones_Cubiertas":"--",
      "Poblacion_Votante":123520000,
      "Avance":"10%",
      "Status":"Bajo"

  }, 
  {
       "Entidad":"Chihuahua",
       "Afiliados":155918,
       "Comite_Estatal":1,
       "Distritos_Federales":9,
       "Distritos_Locales":22,
       "Comites_Municipales":4,
       "Secciones_Cubiertas":200,
       "Poblacion_Votante":2885919,
       "Avance":"10%",
       "Status":"Bajo"

   }
]